<DOMSymbolItem xmlns:xsi="http://www.w3.org/2001/XMLSchema-instance" xmlns="http://ns.adobe.com/xfl/2008/" name="_player/parts/тело_С" itemID="53775598-00000087" symbolType="graphic" lastModified="1406145125">
  <timeline>
    <DOMTimeline name="тело_С">
      <layers>
        <DOMLayer name="Layer 1" color="#4FFF4F" current="true" isSelected="true">
          <frames>
            <DOMFrame index="0" keyMode="9728">
              <elements>
                <DOMShape>
                  <fills>
                    <FillStyle index="1">
                      <SolidColor color="#6376C2"/>
                    </FillStyle>
                    <FillStyle index="2">
                      <SolidColor/>
                    </FillStyle>
                  </fills>
                  <edges>
                    <Edge fillStyle0="1" fillStyle1="2" edges="!33 -71S3|-13 -70!-13 -70[-26 -64 -56 -55!-56 -55[-83 -48 -92 -42!-92 -42[-96 -42 -111 -26!-111 -26|-111 -27!-111 -27[-113 -33 -120 -33!-120 -33[-136 -33 -141 1!-141 1[-142 13 -142 39!-142 39[-142 58 -124 73!-124 73[-102 90 -64 90!-64
 90[-56 90 -20 83!-20 83[-10 87 2 87!2 87[24 87 42 79!42 79[45 78 46 77!46 77|53 77!53 77[116 64 120 63!120 63[143 55 143 33!143 33|145 -6!145 -6[145 -29 129 -38!129 -38[129 -37 129 -35!129 -35[122 -49 109 -57!109 -57|108 -56!108 -56
[109 -51 108 -44!108 -44[106 -39 105 -36!105 -36[82 -64 54 -70!54 -70[34 -69 33 -71"/>
                    <Edge fillStyle1="2" edges="
!152 -28S2[154 -22 156 -12!156 -12[160 9 158 40!158 40[156 62 144 69!144 69[143 69 93 85!93 85[19 106 -27 107!-27 107[-106 107 -134 94!-134 94[-159 81 -160 53!-160 53[-155 9 -149 -12!-149 -12|-149 -14!-149 -14[-152 -43 -105 -71!-105 -71
[-62 -100 -16 -105!-16 -105|40 -107!40 -107[87 -109 123 -72!123 -72[147 -49 152 -28"/>
                    <Edge cubics="!123 -72(;139,-57 149,-42 152,-28q123 -72Q147 -49q152 -28);"/>
                    <Edge cubics="!152 -28(;153,-24 155,-19 156,-12q152 -28Q154 -22q156 -12);"/>
                    <Edge cubics="!54 -70(;41,-69 34,-70 33,-71q54 -70Q34 -69q33 -71);"/>
                    <Edge cubics="!158 40(158,40;156,55 152,64 144,69q158 40Q156 62q144 69)144,69;"/>
                    <Edge cubics="!40 -107(;72,-108 99,-97 123,-72q40 -107Q87 -109q123 -72);"/>
                    <Edge cubics="!144 69(144,69;143,69 126,74 93,85q144 69Q143 69q93 85);"/>
                    <Edge cubics="!156 -12(156,-12;158,2 159,19 158,40q156 -12Q160 9q158 40);"/>
                    <Edge cubics="!-13 -70(;-22,-66 -36,-61 -56,-55q-13 -70Q-26 -64q-56 -55);"/>
                    <Edge cubics="!-27 107(-27,107;-80,107 -115,103 -134,94q-27 107Q-106 107q-134 94);"/>
                    <Edge cubics="!-105 -71(;-77,-90 -47,-102 -16,-105q-105 -71Q-62 -100q-16 -105);"/>
                    <Edge cubics="!-56 -55(-56,-55;-74,-50 -86,-46 -92,-42q-56 -55Q-83 -48q-92 -42);"/>
                    <Edge cubics="!-160 53(-160,53;-157,24 -153,2 -149,-12q-160 53Q-155 9q-149 -12);"/>
                    <Edge cubics="!-149 -12(;-149,-12 -149,-14 -149,-14q-149 -12 -149 -14);"/>
                    <Edge cubics="!-134 94(;-150,85 -159,72 -160,53q-134 94Q-159 81q-160 53);"/>
                    <Edge cubics="!-149 -14(;-151,-33 -136,-52 -105,-71q-149 -14Q-152 -43q-105 -71);"/>
                    <Edge cubics="!93 85(;44,99 4,106 -27,107q93 85Q19 106q-27 107);"/>
                    <Edge cubics="!-16 -105(;-16,-105 40,-107 40,-107q-16 -105 40 -107);"/>
                    <Edge cubics="!33 -71(;33,-71 -13,-70 -13,-70q33 -71 -13 -70);"/>
                    <Edge cubics="!-64 90(-64,90;-119,90 -142,61 -142,39q-64 90Q-102 90q-124 73Q-142 58q-142 39);"/>
                    <Edge cubics="!-142 39(-142,39;-142,33 -145,-33 -120,-33q-142 39Q-142 13q-141 1Q-136 -33q-120 -33);"/>
                    <Edge cubics="!108 -56(108,-56;108,-56 109,-57 109,-57q108 -56 109 -57);"/>
                    <Edge cubics="!145 -6(145,-6;145,-4 143,27 143,33q145 -6 143 33);"/>
                    <Edge cubics="!143 33(143,33;143,66 112,65 53,77q143 33Q143 55q120 63Q116 64q53 77)53,77;"/>
                    <Edge cubics="!129 -38(;144,-29 145,-18 145,-6q129 -38Q145 -29q145 -6);"/>
                    <Edge cubics="!129 -35(;129,-36 129,-37 129,-38q129 -35Q129 -37q129 -38);"/>
                    <Edge cubics="!109 -57(109,-57;118,-52 125,-44 129,-35q109 -57Q122 -49q129 -35);"/>
                    <Edge cubics="!105 -36(105,-36;106,-38 107,-41 108,-44q105 -36Q106 -39q108 -44);"/>
                    <Edge cubics="!108 -44(;109,-49 109,-53 108,-56q108 -44Q109 -51q108 -56);"/>
                    <Edge cubics="!53 77(;53,77 46,77 46,77q53 77 46 77);"/>
                    <Edge cubics="!46 77(;45,78 44,78 42,79q46 77Q45 78q42 79);"/>
                    <Edge cubics="!105 -36(;89,-55 72,-66 54,-70q105 -36Q82 -64q54 -70);"/>
                    <Edge cubics="!-120 -33(-120,-33;-115,-33 -112,-31 -111,-27q-120 -33Q-113 -33q-111 -27);"/>
                    <Edge cubics="!-111 -27(-111,-27;-111,-27 -111,-26 -111,-26q-111 -27 -111 -26);"/>
                    <Edge cubics="!-92 -42(;-94,-42 -101,-37 -111,-26q-92 -42Q-96 -42q-111 -26);"/>
                    <Edge cubics="!2 87(;-6,87 -13,86 -20,83q2 87Q-10 87q-20 83);"/>
                    <Edge cubics="!-20 83(;-44,88 -58,90 -64,90q-20 83Q-56 90q-64 90);"/>
                    <Edge cubics="!42 79(;31,84 17,87 2,87q42 79Q24 87q2 87);"/>
                  </edges>
                </DOMShape>
              </elements>
            </DOMFrame>
          </frames>
        </DOMLayer>
      </layers>
    </DOMTimeline>
  </timeline>
</DOMSymbolItem>