<DOMSymbolItem xmlns:xsi="http://www.w3.org/2001/XMLSchema-instance" xmlns="http://ns.adobe.com/xfl/2008/" name="_player/parts/_головы/голова_право" itemID="53cabfa5-000000f3" symbolType="graphic" lastModified="1406145125">
  <timeline>
    <DOMTimeline name="голова_право">
      <layers>
        <DOMLayer name="шляпа" color="#9933CC" current="true" isSelected="true" autoNamed="false">
          <frames>
            <DOMFrame index="0" keyMode="9728">
              <elements>
                <DOMSymbolInstance libraryItemName="_player/parts/_головы/шляпа_влево" centerPoint3DX="45.8" centerPoint3DY="7.45">
                  <matrix>
                    <Matrix a="0.981857299804688" b="-0.189529418945313" c="0.189529418945313" d="0.981857299804688" tx="48.15" ty="14.7"/>
                  </matrix>
                  <transformationPoint>
                    <Point x="-1.1" y="-7.25"/>
                  </transformationPoint>
                </DOMSymbolInstance>
              </elements>
            </DOMFrame>
          </frames>
        </DOMLayer>
        <DOMLayer name="волосы_текстура" color="#FF4FFF" outline="true" useOutlineView="true" autoNamed="false">
          <frames>
            <DOMFrame index="0" keyMode="9728">
              <elements>
                <DOMShape>
                  <fills>
                    <FillStyle index="1">
                      <SolidColor alpha="0.301960784313725"/>
                    </FillStyle>
                  </fills>
                  <edges>
                    <Edge fillStyle0="1" edges="!1076 742[1206 743 1328 690!1328 690[1407 656 1443 582!1443 582[1463 542 1423 526!1423 526[1418 528 1414 531!1414 531[1409 533 1407 538!1407 538[1405 543 1407 546!1407 546[1407 548 1408 549!1408 549[1408 550 1409 551!1409 551[1410 553
 1412 554!1412 554[1415 556 1418 559!1418 559[1378 636 1292 668!1292 668[1221 695 1148 716!1148 716[1108 728 1076 742!1014 609[960 656 945 723!945 723[936 761 941 796!941 796[938 751 960 712!960 712[997 649 1055 602!1055 602[1104 563
 1124 524!1124 524[1067 562 1014 609!947 874[870 946 854 1053!854 1053[838 1158 893 1251!893 1251[#38F.DC #503.55 933.5 1314!933.5 1314[#39D.1F #536.92 916 1355!916 1355[888 1419 889 1487!889 1487[#385.59 #578.94 937.5 1319.5!937.5 1319.5
[#3B2.01 #533.5B 955 1343!955 1343[#3B2.45 #532.81 938.5 1317.5!938.5 1317.5[#3B7.96 #507.DB 968 1259!968 1259[1013 1180 1033 1090!1033 1090[1049 1014 1086 946!1086 946[1101 919 1092 902!1092 902[1024 1002 994 1124!994 1124[#3CB.78 #4C3.C3
 934.5 1311!934.5 1311[#383.5 #4E2.9B 882 1179!882 1179[857 1079 898 984!898 984[926 919 947 874!755 719[788 649 822 588!822 588[750 673 711 780!711 780[671 888 675 1000!675 1000[677 1062 705 1118!705 1118[680 1029 693 934!693 934[708
 822 755 719!543 917[519 976 516 1041!516 1041[512 1103 514 1166!514 1166[516 1201 520 1235!520 1235[517 1174 523 1114!523 1114[530 1051 537 989!537 989[541 948 543 917!573 1287[559 1361 542 1434!542 1434[533 1476 523 1519!523 1519[550
 1454 570 1374!570 1374[588 1299 600 1221!600 1221[607 1177 616 1143!616 1143[586 1211 573 1287!749 1492[763 1436 747 1391!747 1391[750 1485 714 1583!714 1583[681 1676 657 1772!657 1772[644 1825 618 1873!618 1873[672 1791 699 1687!699
 1687[724 1588 749 1492!786 1612[774 1678 762 1746!762 1746[749 1814 744 1880!744 1880[741 1918 747 1956!747 1956[746 1888 763 1823!763 1823[781 1756 788 1688!788 1688[793 1646 786 1612!971 1325|972 1325!972 1325[972 1329 970 1333!970
 1333[969 1337 969 1341!969 1341[969 1343 968 1345!968 1345[965 1342 965 1338!965 1338[965 1334 967 1330!967 1330[968 1327 971 1325!968 1312[961 1326 959 1340!959 1340[958 1351 967 1353!967 1353[963 1435 979 1516!979 1516[998 1609 1056
 1685!1056 1685[1087 1724 1121 1758!1121 1758[1052 1676 1020 1575!1020 1575[990 1485 992 1390!992 1390[994 1331 987 1287!987 1287[976 1298 968 1312!922 1610[914 1673 895 1734!895 1734[884 1769 867 1803!867 1803[903 1744 926 1673!926 1673
[946 1611 951 1545!951 1545[954 1509 940 1485!940 1485[931 1546 922 1610"/>
                  </edges>
                </DOMShape>
              </elements>
            </DOMFrame>
          </frames>
        </DOMLayer>
        <DOMLayer name="нос" color="#4FFF4F" outline="true" useOutlineView="true" autoNamed="false">
          <frames>
            <DOMFrame index="0" keyMode="9728">
              <elements>
                <DOMShape>
                  <fills>
                    <FillStyle index="1">
                      <SolidColor color="#F3D2AB"/>
                    </FillStyle>
                  </fills>
                  <strokes>
                    <StrokeStyle index="1">
                      <SolidStroke scaleMode="normal" weight="0.1">
                        <fill>
                          <SolidColor color="#CDB18F"/>
                        </fill>
                      </SolidStroke>
                    </StrokeStyle>
                  </strokes>
                  <edges>
                    <Edge fillStyle1="1" strokeStyle="1" edges="
!1710 1032[1785 1089 1804 1183!1804 1183[1817 1251 1732 1254!1732 1254[#6A0.4F #4E7.59 1684 1246"/>
                    <Edge fillStyle1="1" edges="
!1684 1246[#68E.54 #4D9.2F 1678 1234!1678 1234[1676 1221 1691 1202!1691 1202[1702 1189 1722 1186!1722 1186[1728 1184 1734 1183!1734 1183[1727 1158 1715 1134!1715 1134[1701 1105 1690 1074!1690 1074[1680 1042 1710 1032"/>
                    <Edge cubics="!1710 1032(;1760,1070 1791,1120 1804,1183q1710 1032Q1785 1089q1804 1183);"/>
                    <Edge cubics="!1690 1074(1690,1074;1683,1053 1690,1039 1710,1032q1690 1074Q1680 1042q1710 1032);"/>
                    <Edge cubics="!1715 1134(1715,1134;1706,1115 1697,1095 1690,1074q1715 1134Q1701 1105q1690 1074)1690,1074;"/>
                    <Edge cubics="!1734 1183(;1729,1166 1723,1150 1715,1134q1734 1183Q1727 1158q1715 1134);"/>
                    <Edge cubics="!1722 1186(1722,1186;1726,1185 1730,1184 1734,1183q1722 1186Q1728 1184q1734 1183);"/>
                    <Edge cubics="!1691 1202(;1698,1193 1709,1188 1722,1186q1691 1202Q1702 1189q1722 1186);"/>
                    <Edge cubics="!1678 1234(1678,1234;1677,1225 1681,1215 1691,1202q1678 1234Q1676 1221q1691 1202)1691,1202;"/>
                    <Edge cubics="!1732 1254(;1697,1255 1679,1249 1678,1234q1732 1254Q1679 1256q1678 1234);"/>
                    <Edge cubics="!1804 1183(1804,1183;1813,1228 1789,1252 1732,1254q1804 1183Q1817 1251q1732 1254);"/>
                  </edges>
                </DOMShape>
              </elements>
            </DOMFrame>
          </frames>
        </DOMLayer>
        <DOMLayer name="борода_текстура" color="#4FFFFF" outline="true" useOutlineView="true" autoNamed="false">
          <frames>
            <DOMFrame index="0" keyMode="9728">
              <elements>
                <DOMShape>
                  <fills>
                    <FillStyle index="1">
                      <SolidColor alpha="0.301960784313725"/>
                    </FillStyle>
                  </fills>
                  <edges>
                    <Edge fillStyle0="1" edges="
!1635 1308[1621 1327 1609 1348!1609 1348[1597 1368 1583 1385!1583 1385[1574 1397 1565 1410!1565 1410[1585 1392 1603 1369!1603 1369[1618 1349 1634 1329!1634 1329[1645 1313 1635 1308!1716 1289[1718 1277 1708 1276!1708 1276[1704 1288 1703
 1302!1703 1302[1701 1316 1695 1327!1695 1327[1691 1335 1689 1342!1689 1342[1704 1333 1710 1315!1710 1315[1714 1302 1716 1289!1789 1519[1778 1493 1753 1487!1753 1487[1762 1502 1782 1531!1782 1531[1799 1556 1805 1586!1805 1586[1808 1604
 1814 1621!1814 1621[1814 1599 1808 1575!1808 1575[1801 1546 1789 1519!1636 1530[1653 1556 1668 1585!1668 1585[1683 1615 1689 1647!1689 1647[1692 1665 1697 1683!1697 1683[1697 1657 1689 1626!1689 1626[1681 1593 1667 1563!1667 1563[1656
 1541 1636 1530!1752 1587[1749 1663 1744 1738!1744 1738[1739 1814 1746 1889!1746 1889[1750 1932 1753 1975!1753 1975[1753 1902 1755 1824!1755 1824[1757 1747 1762 1670!1762 1670[1764 1625 1752 1587!1716 1918[1723 1962 1720 2011!1720 2011
[1717 2059 1722 2107!1722 2107[1725 2136 1735 2163!1735 2163[1727 2117 1728 2068!1728 2068[1728 2018 1729 1969!1729 1969[1729 1938 1716 1918!1545 1407[1517 1452 1495 1502!1495 1502[1472 1552 1479 1606!1479 1606[1483 1635 1488 1665!1488
 1665[1483 1622 1489 1575!1489 1575[1496 1516 1528 1466!1528 1466[1551 1429 1545 1407!1151 1606[1146 1566 1139 1526!1139 1526[1135 1500 1127 1480!1127 1480[1127 1520 1137 1560!1137 1560[1146 1600 1149 1640!1149 1640[1150 1664 1154 1686
!1154 1686[1156 1647 1151 1606!1561 1588[1560 1611 1561 1635!1561 1635[1562 1648 1566 1660!1566 1660[1569 1641 1569 1616!1569 1616[1570 1593 1569 1569!1569 1569[1568 1551 1564 1541!1564 1541[1562 1564 1561 1588!1437 1569[1432 1604 1436
 1640!1436 1640[1439 1659 1446 1677!1446 1677[1443 1645 1444 1611!1444 1611[1445 1571 1454 1538!1454 1538[1462 1513 1457 1503!1457 1503[1441 1535 1437 1569!1558 1653[1576 1710 1591 1772!1591 1772[1606 1834 1614 1898!1614 1898[1618 1934
 1622 1970!1622 1970[1625 1912 1618 1850!1618 1850[1611 1784 1593 1721!1593 1721[1582 1680 1558 1653!1352 1521[1353 1523 1355 1524!1355 1524[1344 1595 1339 1668!1339 1668[1335 1745 1369 1812!1369 1812[1388 1850 1415 1880!1415 1880[1366
 1819 1356 1742!1356 1742[1346 1669 1355 1597!1355 1597[1359 1560 1361 1524!1361 1524[1359 1521 1357 1519!1357 1519[1355 1516 1352 1514!1352 1514[1351 1513 1349 1512!1349 1512[1348 1512 1346 1512!1346 1512[1347 1515 1348 1517!1348 1517
[1349 1518 1351 1519!1351 1519[1352 1520 1352 1521!1332 1892[1335 1879 1326 1856!1326 1856[1318 1838 1314 1818!1314 1818[1311 1805 1301 1800!1301 1800[1305 1818 1311 1836!1311 1836[1316 1855 1324 1872!1324 1872[1329 1882 1332 1892!1503
 1883[1496 1909 1499 1936!1499 1936[1501 1963 1502 1990!1502 1990[1503 2006 1506 2021!1506 2021[1508 1998 1505 1969!1505 1969[1503 1942 1504 1915!1504 1915[1505 1896 1503 1883"/>
                  </edges>
                </DOMShape>
              </elements>
            </DOMFrame>
          </frames>
        </DOMLayer>
        <DOMLayer name="борода" color="#4F80FF" outline="true" useOutlineView="true" autoNamed="false">
          <frames>
            <DOMFrame index="0" keyMode="9728">
              <elements>
                <DOMShape>
                  <fills>
                    <FillStyle index="1">
                      <SolidColor color="#FFFFFF"/>
                    </FillStyle>
                  </fills>
                  <strokes>
                    <StrokeStyle index="1">
                      <SolidStroke scaleMode="normal" weight="0.1">
                        <fill>
                          <SolidColor color="#D0D0D0"/>
                        </fill>
                      </SolidStroke>
                    </StrokeStyle>
                  </strokes>
                  <edges>
                    <Edge fillStyle1="1" strokeStyle="1" edges="
!1664 1254[1684 1248 1708 1246!1708 1246[1708 1244 1710 1245!1710 1245[1714 1238 1721 1237!1721 1237[1755 1246 1763 1272!1763 1272[1762 1279 1762 1288!1762 1288[1762 1292 1767 1295!1767 1295[1767 1308 1759 1332!1759 1332[1745 1358 1735
 1345!1735 1345[1719 1357 1704 1352!1704 1352[1702 1354 1699 1356!1699 1356[1677 1368 1668 1380!1668 1380|1666 1380!1666 1380[1661 1382 1658 1385!1658 1385[1644 1379 1630 1379!1630 1379[1592 1396 1565 1429!1565 1429[1471 1523 1575 1529
!1575 1529[1603 1528 1631 1503!1631 1503[1631 1501 1633 1501!1633 1501[1664 1528 1696 1483!1696 1483[1717 1480 1740 1477!1740 1477[1737 1480 1741 1482!1741 1482[1742 1476 1749 1472!1749 1472[1763 1466 1766 1478!1766 1478|1768 1480!1768
 1480[1797 1509 1808 1560!1808 1560[1817 1611 1802 1664!1802 1664[1799 1670 1796 1678!1796 1678[1812 1747 1827 1817!1827 1817[1806 1826 1814 1850!1814 1850[1827 1880 1837 1913!1837 1913[1815 1941 1826 1986!1826 1986[1826 1991 1828 1998
!1828 1998[1820 2007 1814 2016!1814 2016[1814 2027 1820 2036!1820 2036[1838 2114 1799 2179!1799 2179[1793 2183 1788 2192!1788 2192[1785 2209 1789 2229!1789 2229[1786 2255 1783 2283!1783 2283[1771 2293 1760 2301!1760 2301[1755 2301 1756
 2303!1756 2303[1741 2304 1733 2300!1733 2300[1729 2294 1727 2291!1727 2291[1719 2294 1711 2295!1711 2295[1706 2303 1699 2307!1699 2307[1672 2276 1654 2240!1654 2240[1646 2230 1644 2217!1644 2217[1620 2173 1589 2150!1589 2150[1587 2115
 1565 2095!1565 2095[1561 2103 1558 2112!1558 2112[1541 2131 1522 2132!1522 2132[1510 2130 1506 2123!1506 2123[1460 2159 1445 2111!1445 2111[1434 2085 1428 2060!1428 2060[1420 2031 1414 2008!1414 2008[1410 1996 1401 2006!1401 2006[1386
 2014 1374 2015!1374 2015[1366 2013 1362 2011!1362 2011[1302 2024 1285 1968!1285 1968[1275 1936 1266 1907!1266 1907[1250 1876 1233 1847!1233 1847[1147 1843 1119 1765!1119 1765[1095 1709 1077 1652"/>
                    <Edge fillStyle1="1" edges="
!1077 1652[1068 1634 1070 1615!1070 1615[1069 1591 1079 1569!1079 1569[1054 1538 1041 1502!1041 1502[1037 1496 1038 1493!1038 1493[1028 1480 1022 1468!1022 1468[1018 1464 1018 1462"/>
                    <Edge fillStyle1="1" strokeStyle="1" edges="
!1018 1462|1018 1460!1018 1460|1017 1458!1017 1458|1018 1458"/>
                    <Edge fillStyle1="1" edges="
!1018 1458[1016 1456 1017 1455!1017 1455[1015 1442 1032 1432!1032 1432[1036 1431 1042 1432!1042 1432[1045 1431 1048 1433!1048 1433[1049 1434 1055 1436"/>
                    <Edge fillStyle1="1" strokeStyle="1" edges="
!1055 1436|1055 1438!1055 1438[1057 1433 1064 1431"/>
                    <Edge fillStyle1="1" edges="
!1064 1431[1041 1385 1099 1362!1099 1362[1133 1365 1147 1393!1147 1393[1159 1419 1181 1440!1181 1440[1193 1452 1204 1464!1204 1464[1209 1464 1215 1465!1215 1465[1220 1466 1224 1468!1224 1468[1231 1470 1237 1474!1237 1474[1238 1475 1240
 1477!1240 1477[1261 1473 1281 1478!1281 1478[1285 1475 1289 1472!1289 1472[1304 1474 1328 1458!1328 1458[1345 1441 1359 1433!1359 1433[1355 1455 1371 1469!1371 1469[1412 1504 1438 1453!1438 1453[1461 1451 1487 1389!1487 1389[1517 1384
 1535 1354!1535 1354[1543 1331 1553 1312!1553 1312[1577 1284 1616 1287!1616 1287[1654 1291 1631 1273!1631 1273|1658 1262!1658 1262[1627 1259 1664 1254"/>
                  </edges>
                </DOMShape>
              </elements>
            </DOMFrame>
          </frames>
        </DOMLayer>
        <DOMLayer name="волосы" color="#00CC00" outline="true" useOutlineView="true" autoNamed="false">
          <frames>
            <DOMFrame index="0" keyMode="9728">
              <elements>
                <DOMShape>
                  <fills>
                    <FillStyle index="1">
                      <SolidColor color="#FFFFFF"/>
                    </FillStyle>
                  </fills>
                  <strokes>
                    <StrokeStyle index="1">
                      <SolidStroke scaleMode="normal" weight="0.1">
                        <fill>
                          <SolidColor color="#D0D0D0"/>
                        </fill>
                      </SolidStroke>
                    </StrokeStyle>
                  </strokes>
                  <edges>
                    <Edge fillStyle1="1" strokeStyle="1" edges="
!1627 638[1626 663 1621 688!1621 688[1616 712 1592 708!1592 708[1580 706 1568 703!1568 703[1568 716 1558 725!1558 725[1541 738 1522 730!1522 730[1519 729 1518 728!1518 728[1507 740 1502 753!1502 753[1448 762 1398 778!1398 778[1388 779
 1385 788!1385 788[1355 786 1336 803!1336 803[1311 818 1299 843!1299 843[1286 857 1271 871!1271 871[1255 869 1242 872!1242 872[1211 907 1184 945!1184 945[1163 975 1144 1004!1144 1004[1139 1004 1135 1005!1135 1005[1156 944 1191 890!1191
 890[1197 880 1204 871!1204 871[1183 868 1163 867!1163 867[1091 894 1078 938!1078 938[1070 951 1071 964!1071 964[1069 965 1070 967!1070 967[1069 970 1069 974!1069 974|1071 974!1071 974[1069 976 1068 979!1068 979[1065 1007 1062 1036!1062
 1036[1058 1051 1057 1066!1057 1066[1045 1075 1036 1089!1036 1089[1013 1123 1009 1156!1009 1156[975 1209 979 1285!979 1285[983 1338 1032 1353!1032 1353[1078 1367 1112 1365!1112 1365[1121 1402 1134 1438!1134 1438[1161 1512 1145 1579!1145
 1579[1143 1586 1133 1589!1133 1589[1139 1616 1137 1640!1137 1640[1189 1641 1186 1689!1186 1689[1184 1736 1150 1768!1150 1768[1142 1774 1138 1774!1138 1774[1129 1774 1125 1763!1125 1763[1119 1754 1118 1743!1118 1743|1118 1742!1118 1742
[1106 1740 1101 1733!1101 1733[1097 1729 1095 1727!1095 1727[1096 1730 1094 1734!1094 1734[1092 1741 1090 1749!1090 1749[1089 1757 1080 1761!1080 1761[1078 1762 1075 1762!1075 1762[1071 1761 1069 1761!1069 1761[1065 1759 1062 1757!1062
 1757[1054 1734 1060 1709!1060 1709[1053 1706 1052 1702!1052 1702[1048 1717 1045 1735!1045 1735[1039 1757 1032 1758!1032 1758[1025 1757 1016 1735!1016 1735[1015 1732 1015 1730!1015 1730[1003 1742 987 1740!987 1740[985 1741 983 1743!983
 1743[971 1745 965 1741!965 1741[958 1753 949 1765!949 1765[935 1784 917 1800!917 1800[896 1821 865 1809!865 1809[859 1816 852 1823!852 1823[844 1833 832 1837!832 1837[831 1842 831 1846!831 1846[822 1919 811 1991!811 1991[804 2042 751
 2024!751 2024[738 2076 727 2126!727 2126[723 2141 718 2154!718 2154[696 2202 663 2159!663 2159[646 2138 658 2113!658 2113[646 2084 648 2054!648 2054[635 2082 618 2109!618 2109[596 2018 604 1915!604 1915[584 2002 582 2092!582 2092[561
 1944 557 1766!557 1766[556 1700 553 1635!553 1635[548 1650 541 1665!541 1665[511 1738 490 1817!490 1817[497 1698 516 1554!516 1554[527 1473 537 1391!537 1391[536 1358 539 1330!539 1330[526 1276 512 1222!512 1222[502 1186 506 1151!506
 1151[510 1122 503 1101!503 1101[502 1079 502 1058!502 1058[484 1116 485 1177!485 1177[453 1064 472 942!472 942[496 795 556 659!556 659[606 546 723 504!723 504[732 505 740 508!740 508[782 472 830 443!830 443[908 425 988 412!988 412[1052
 406 1117 402!1117 402[1070 397 1023 394!1023 394[981 392 938 403!938 403|938 401!938 401[947 397 958 394!958 394[967 391 978 388!978 388[989 386 999 381!999 381[1027 370 1060 370!1060 370[1075 370 1082 366!1082 366[1129 369 1177 374
!1177 374[1219 379 1261 387!1261 387[1279 390 1294 394!1294 394[1299 394 1304 394!1304 394[1360 403 1414 422!1414 422[1468 438 1516 464!1516 464[1562 460 1592 509!1592 509[1613 542 1620 581!1620 581[1626 610 1627 638"/>
                  </edges>
                </DOMShape>
              </elements>
            </DOMFrame>
          </frames>
        </DOMLayer>
        <DOMLayer name="бровь_правая" color="#FF0000" outline="true" useOutlineView="true" autoNamed="false">
          <frames>
            <DOMFrame index="0" keyMode="9728">
              <elements>
                <DOMShape>
                  <fills>
                    <FillStyle index="1">
                      <SolidColor color="#F0F0F0"/>
                    </FillStyle>
                  </fills>
                  <edges>
                    <Edge fillStyle0="1" edges="
!1631 962[1630 956 1629 952!1629 952[1624 925 1604 926!1604 926[1598 926 1593 934!1593 934[1578 927 1562 928!1562 928[1558 928 1555 930!1555 930[1550 930 1546 933!1546 933[1540 934 1534 937!1534 937[1522 939 1510 950!1510 950[1495 949
 1480 954!1480 954[1453 963 1423 972!1423 972[1400 984 1378 1001!1378 1001[1375 1007 1373 1013!1373 1013[1357 1036 1351 1064!1351 1064[1336 1102 1333 1145!1333 1145[1334 1158 1335 1178!1335 1178|1339 1177!1339 1177[1339 1166 1343 1156
!1343 1156[1356 1091 1395 1065!1395 1065[1411 1045 1431 1033!1431 1033[1449 1018 1474 1011!1474 1011[1504 1006 1529 1003!1529 1003[1557 1008 1588 1014!1588 1014[1630 1018 1632 974!1632 974[1631 968 1631 962"/>
                    <Edge cubics="!1562 928(1562,928;1559,928 1557,929 1555,930q1562 928Q1558 928q1555 930);"/>
                    <Edge cubics="!1555 930(;1552,930 1549,931 1546,933q1555 930Q1550 930q1546 933);"/>
                    <Edge cubics="!1546 933(;1542,934 1538,935 1534,937q1546 933Q1540 934q1534 937);"/>
                    <Edge cubics="!1534 937(;1526,938 1518,943 1510,950q1534 937Q1522 939q1510 950);"/>
                    <Edge cubics="!1510 950(;1500,949 1490,951 1480,954q1510 950Q1495 949q1480 954);"/>
                    <Edge cubics="!1632 974(;1631,970 1631,966 1631,962q1632 974Q1631 968q1631 962);"/>
                    <Edge cubics="!1604 926(;1600,926 1596,929 1593,934q1604 926Q1598 926q1593 934);"/>
                    <Edge cubics="!1629 952(;1626,934 1617,925 1604,926q1629 952Q1624 925q1604 926);"/>
                    <Edge cubics="!1631 962(;1630,958 1630,955 1629,952q1631 962Q1630 956q1629 952);"/>
                    <Edge cubics="!1593 934(;1583,929 1573,927 1562,928q1593 934Q1578 927q1562 928);"/>
                    <Edge cubics="!1480 954(;1462,960 1443,966 1423,972q1480 954Q1453 963q1423 972);"/>
                    <Edge cubics="!1474 1011(;1494,1008 1512,1005 1529,1003q1474 1011Q1504 1006q1529 1003);"/>
                    <Edge cubics="!1529 1003(;1548,1006 1567,1010 1588,1014q1529 1003Q1557 1008q1588 1014);"/>
                    <Edge cubics="!1373 1013(;1362,1028 1355,1045 1351,1064q1373 1013Q1357 1036q1351 1064);"/>
                    <Edge cubics="!1395 1065(1395,1065;1406,1052 1418,1041 1431,1033q1395 1065Q1411 1045q1431 1033);"/>
                    <Edge cubics="!1343 1156(1343,1156;1352,1113 1369,1082 1395,1065q1343 1156Q1356 1091q1395 1065);"/>
                    <Edge cubics="!1351 1064(;1341,1089 1335,1116 1333,1145q1351 1064Q1336 1102q1333 1145);"/>
                    <Edge cubics="!1333 1145(;1334,1154 1334,1165 1335,1178q1333 1145Q1334 1158q1335 1178);"/>
                    <Edge cubics="!1339 1177(;1339,1170 1340,1163 1343,1156q1339 1177Q1339 1166q1343 1156);"/>
                    <Edge cubics="!1335 1178(1335,1178;1335,1178 1339,1177 1339,1177q1335 1178 1339 1177);"/>
                    <Edge cubics="!1378 1001(;1376,1005 1374,1009 1373,1013q1378 1001Q1375 1007q1373 1013);"/>
                    <Edge cubics="!1431 1033(;1443,1023 1457,1016 1474,1011q1431 1033Q1449 1018q1474 1011);"/>
                    <Edge cubics="!1588 1014(;1616,1017 1631,1003 1632,974q1588 1014Q1630 1018q1632 974);"/>
                    <Edge cubics="!1423 972(;1408,980 1393,990 1378,1001q1423 972Q1400 984q1378 1001);"/>
                  </edges>
                </DOMShape>
              </elements>
            </DOMFrame>
          </frames>
        </DOMLayer>
        <DOMLayer name="зрачок_правый" color="#FF0000" outline="true" useOutlineView="true" autoNamed="false">
          <frames>
            <DOMFrame index="0" keyMode="9728">
              <elements>
                <DOMShape>
                  <fills>
                    <FillStyle index="1">
                      <SolidColor/>
                    </FillStyle>
                  </fills>
                  <edges>
                    <Edge fillStyle1="1" edges="
!1548 1116[1554 1106 1564 1104!1564 1104[1573 1101 1579 1110!1579 1110[1586 1118 1587 1131!1587 1131[1586 1144 1579 1155!1579 1155[1573 1165 1564 1168!1564 1168[1554 1170 1548 1161!1548 1161[1541 1153 1541 1140!1541 1140[1541 1127 1548
 1116"/>
                  </edges>
                </DOMShape>
              </elements>
            </DOMFrame>
          </frames>
        </DOMLayer>
        <DOMLayer name="глаз_правый" color="#FF0000" outline="true" useOutlineView="true" autoNamed="false">
          <frames>
            <DOMFrame index="0" keyMode="9728">
              <elements>
                <DOMShape>
                  <fills>
                    <FillStyle index="1">
                      <SolidColor color="#FFFFFF"/>
                    </FillStyle>
                  </fills>
                  <edges>
                    <Edge fillStyle1="1" edges="
!1612 1103[1613 1120 1615 1135!1615 1135[1614 1144 1615 1152!1615 1152[1613 1161 1612 1171!1612 1171[1603 1196 1568 1214!1568 1214[1558 1215 1550 1219!1550 1219[1518 1225 1486 1209!1486 1209[1444 1184 1436 1152!1436 1152[1431 1137 1432
 1126!1432 1126[1431 1107 1443 1093!1443 1093[1462 1065 1500 1055!1500 1055[1507 1050 1518 1050!1518 1050[1544 1044 1570 1054!1570 1054[1602 1062 1612 1103"/>
                  </edges>
                </DOMShape>
              </elements>
            </DOMFrame>
          </frames>
        </DOMLayer>
        <DOMLayer name="рот" color="#FF4F4F" outline="true" useOutlineView="true" autoNamed="false">
          <frames>
            <DOMFrame index="0" keyMode="9728">
              <elements>
                <DOMShape>
                  <fills>
                    <FillStyle index="1">
                      <SolidColor alpha="0.301960784313725"/>
                    </FillStyle>
                  </fills>
                  <edges>
                    <Edge fillStyle1="1" edges="
!1734 1428[1742 1426 1750 1429!1750 1429[1759 1431 1764 1436!1764 1436[1732 1446 1697 1459!1697 1459[1650 1476 1601 1470!1601 1470[1584 1468 1582 1456!1582 1456[1606 1434 1650 1433!1650 1433[1686 1432 1719 1426!1719 1426[1727 1430 1734
 1428!1574 1228[1571 1247 1546 1264!1546 1264[1526 1278 1505 1290!1505 1290[1487 1300 1470 1297!1470 1297[1481 1272 1510 1259!1510 1259[1532 1250 1553 1236!1553 1236[1563 1230 1574 1228"/>
                  </edges>
                </DOMShape>
              </elements>
            </DOMFrame>
          </frames>
        </DOMLayer>
        <DOMLayer name="тени" color="#FF4F4F" outline="true" useOutlineView="true" autoNamed="false">
          <frames>
            <DOMFrame index="0" keyMode="9728">
              <elements>
                <DOMShape>
                  <fills>
                    <FillStyle index="1">
                      <SolidColor alpha="0.2"/>
                    </FillStyle>
                  </fills>
                  <edges>
                    <Edge fillStyle1="1" edges="
!1623 633[1623 631 1623 628!1623 628[1623 627 1625 627!1625 627[1626 626 1627 626!1627 626[1628 626 1629 626!1629 626[1643 657 1643 693!1643 693[1644 722 1607 735!1607 735[1586 742 1571 734!1571 734[1545 763 1503 776!1503 776[1448 793
 1391 808!1391 808[1371 814 1352 813!1352 813[1339 830 1327 846!1327 846[1310 869 1284 886!1284 886[1253 905 1224 896!1224 896[1219 913 1209 932!1209 932[1185 975 1151 1012!1151 1012[1130 1034 1109 1051!1109 1051[1132 1010 1153 967!1153
 967[1170 930 1183 890!1183 890[1176 891 1168 892!1168 892[1141 896 1118 912!1118 912[1112 917 1105 922!1105 922[1099 971 1084 1019!1084 1019[1067 1078 1045 1134!1045 1134[1040 1148 1032 1160!1032 1160[1032 1162 1031 1164!1031 1164[1016
 1221 1004 1279!1004 1279[998 1312 997 1345!997 1345[998 1346 999 1348!999 1348[1001 1351 1004 1355!1004 1355[1006 1359 1009 1363!1009 1363[956 1318 973 1248!973 1248[987 1182 1006 1117!1006 1117[1012 1096 1024 1079!1024 1079[1030 1027
 1043 976!1043 976[1052 945 1071 920!1071 920[1070 909 1075 898!1075 898[1082 877 1104 863!1104 863[1133 845 1168 836!1168 836[1177 834 1183 833!1183 833[1193 834 1204 833!1204 833[1216 833 1224 840!1224 840[1232 845 1236 853!1236 853
[1233 860 1228 866!1228 866[1228 872 1228 878!1228 878[1244 863 1266 851!1266 851[1294 836 1309 808!1309 808[1327 775 1358 756!1358 756[1362 756 1365 757!1365 757[1369 758 1371 760!1371 760[1374 761 1376 762!1376 762[1385 760 1394 757
!1394 757[1401 753 1411 754!1411 754[1412 754 1414 754!1414 754[1427 749 1443 744!1443 744[1485 732 1525 716!1525 716[1537 711 1548 710!1548 710[1553 705 1560 700!1560 700[1577 686 1596 672!1596 672[1604 667 1609 663!1609 663[1609 665
 1610 667!1610 667[1617 657 1620 644!1620 644[1620 641 1623 638!1623 638[1623 636 1623 633!1789 1318|1788 1319!1788 1319[1785 1322 1781 1323!1781 1323[1779 1324 1775 1326!1775 1326[1759 1360 1722 1377!1722 1377[1689 1392 1657 1382!1657
 1382[1646 1392 1630 1401!1630 1401[1620 1406 1612 1411!1612 1411[1588 1446 1571 1486!1571 1486[1567 1497 1563 1506!1563 1506[1569 1509 1577 1510!1577 1510[1596 1514 1616 1516!1616 1516[1630 1517 1643 1513!1643 1513[1633 1528 1612 1534
!1612 1534[1580 1543 1551 1527!1551 1527[1544 1537 1538 1545!1538 1545[1537 1542 1536 1540!1536 1540[1536 1544 1536 1548!1536 1548[1537 1566 1557 1575!1557 1575[1546 1572 1536 1566!1536 1566[1525 1561 1512 1556!1512 1556[1500 1531 1506
 1505!1506 1505[1513 1475 1530 1450!1530 1450|1530 1449!1530 1449[1531 1432 1545 1417!1545 1417[1567 1395 1595 1379!1595 1379[1608 1367 1626 1360!1626 1360[1627 1361 1627 1363!1627 1363[1628 1362 1629 1362!1629 1362[1628 1356 1632 1348
!1632 1348[1635 1346 1639 1347!1639 1347[1644 1347 1646 1350!1646 1350[1647 1351 1648 1352!1648 1352[1653 1349 1657 1347!1657 1347[1692 1330 1728 1323!1728 1323[1733 1323 1737 1324!1737 1324[1741 1325 1744 1326!1744 1326[1760 1321 1779
 1318!1779 1318[1784 1318 1789 1318!1044 1377[1020 1353 1007 1325!1007 1325[998 1306 1013 1294!1013 1294[1037 1318 1055 1346!1055 1346[1074 1374 1099 1397!1099 1397[1113 1410 1132 1415!1132 1415[1079 1412 1044 1377"/>
                  </edges>
                </DOMShape>
              </elements>
            </DOMFrame>
          </frames>
        </DOMLayer>
        <DOMLayer name="основа" color="#9933CC" outline="true" useOutlineView="true" autoNamed="false">
          <frames>
            <DOMFrame index="0" keyMode="9728">
              <elements>
                <DOMShape>
                  <fills>
                    <FillStyle index="1">
                      <SolidColor color="#F3D2AB"/>
                    </FillStyle>
                  </fills>
                  <strokes>
                    <StrokeStyle index="1">
                      <SolidStroke scaleMode="normal" weight="0.1">
                        <fill>
                          <SolidColor color="#CDB18F"/>
                        </fill>
                      </SolidStroke>
                    </StrokeStyle>
                  </strokes>
                  <edges>
                    <Edge fillStyle1="1" strokeStyle="1" edges="
!1695 838[1716 919 1733 1022!1733 1022[1762 1214 1763 1236!1763 1236[1763 1258 1779 1298!1779 1298[1794 1336 1776 1296!1776 1296|1754 1378!1754 1378[1746 1622 1683 1653!1683 1653[1615 1685 1439 1690!1439 1690[1260 1694 1143 1701!1143
 1701[1127 1701 1112 1702!1112 1702[1006 1701 888 1669!888 1669[861 1661 837 1654!837 1654|836 1632!836 1632|836 1654!836 1654[719 1609 664 1582!664 1582|631 1551!631 1551[608 1522 597 1472!597 1472[587 1426 580 1349!580 1349[579 1335
 578 1322!578 1322[573 1261 574 1183!574 1183[573 1140 575 1091!575 1091[582 1038 613 885!613 885[641 730 736 655!736 655[760 635 784 619!784 619|783 610!783 610[858 567 920 539!920 539[992 506 1129 506!1129 506[1160 506 1195 508!1195
 508[1389 518 1504 580!1504 580[1619 642 1646 699!1646 699[1672 756 1695 838"/>
                    <Edge cubics="!1646 699(;1664,737 1680,783 1695,838q1646 699Q1672 756q1695 838);"/>
                    <Edge cubics="!1195 508(;1324,515 1427,539 1504,580q1195 508Q1389 518q1504 580);"/>
                    <Edge cubics="!920 539(;968,517 1038,506 1129,506q920 539Q992 506q1129 506);"/>
                    <Edge cubics="!1129 506(;1150,506 1172,507 1195,508q1129 506Q1160 506q1195 508);"/>
                    <Edge cubics="!783 610(;833,581 878,557 920,539q783 610 920 539);"/>
                    <Edge cubics="!1504 580(;1581,621 1628,661 1646,699q1504 580Q1619 642q1646 699);"/>
                    <Edge cubics="!1439 1690(;1320,1693 1221,1696 1143,1701q1439 1690Q1260 1694q1143 1701);"/>
                    <Edge cubics="!1143 1701(;1132,1701 1121,1701 1112,1702q1143 1701Q1127 1701q1112 1702);"/>
                    <Edge cubics="!1112 1702(;1041,1701 967,1690 888,1669q1112 1702Q1006 1701q888 1669);"/>
                    <Edge cubics="!888 1669(;872,1664 857,1660 837,1654q888 1669 837 1654);"/>
                    <Edge cubics="!1683 1653(;1638,1674 1556,1687 1439,1690q1683 1653Q1615 1685q1439 1690);"/>
                    <Edge cubics="!1754 1378(;1754,1378 1776,1296 1776,1296q1754 1378 1776 1296);"/>
                    <Edge cubics="!1754 1378(;1748,1541 1725,1632 1683,1653q1754 1378Q1746 1622q1683 1653);"/>
                    <Edge cubics="!1763 1236(;1763,1251 1769,1271 1779,1298q1763 1236Q1763 1258q1779 1298);"/>
                    <Edge cubics="!1779 1298(;1788,1323 1788,1323 1776,1296q1779 1298Q1794 1336q1776 1296);"/>
                    <Edge cubics="!1733 1022(;1753,1150 1762,1221 1763,1236q1733 1022Q1762 1214q1763 1236);"/>
                    <Edge cubics="!1695 838(;1709,892 1721,953 1733,1022q1695 838Q1716 919q1733 1022);"/>
                    <Edge cubics="!783 610(;783,610 784,619 784,619q783 610 784 619);"/>
                    <Edge cubics="!613 885(;631,782 672,705 736,655q613 885Q641 730q736 655);"/>
                    <Edge cubics="!597 1472(;590,1441 584,1400 580,1349q597 1472Q587 1426q580 1349);"/>
                    <Edge cubics="!580 1349(;579,1340 579,1331 578,1322q580 1349Q579 1335q578 1322);"/>
                    <Edge cubics="!664 1582(;664,1582 631,1551 631,1551q664 1582 631 1551);"/>
                    <Edge cubics="!631 1551(;616,1532 605,1505 597,1472q631 1551Q608 1522q597 1472);"/>
                    <Edge cubics="!578 1322(;575,1281 573,1235 574,1183q578 1322Q573 1261q574 1183);"/>
                    <Edge cubics="!574 1183(;573,1154 574,1124 575,1091q574 1183Q573 1140q575 1091);"/>
                    <Edge cubics="!736 655(;753,642 768,630 784,619q736 655Q760 635q784 619);"/>
                    <Edge cubics="!836 1654(;758,1624 701,1600 664,1582q836 1654Q719 1609q664 1582);"/>
                    <Edge cubics="!575 1091(;580,1056 592,987 613,885q575 1091Q582 1038q613 885);"/>
                    <Edge cubics="!836 1632(;836,1632 836,1654 836,1654q836 1632 836 1654);"/>
                    <Edge cubics="!836 1632(;836,1632 837,1654 837,1654q836 1632 837 1654);"/>
                  </edges>
                </DOMShape>
              </elements>
            </DOMFrame>
          </frames>
        </DOMLayer>
      </layers>
    </DOMTimeline>
  </timeline>
</DOMSymbolItem>